Workbook

Sheet Nonprofit Personnel
A1: # | B1: Role | C1: Count | D1: Type | E1: Phase | F1: Salary Low | G1: Salary High | H1: Salary Mid | I1: Fringe Rate | J1: Fringe Cost | K1: Fully Loaded
A2: 1 | B2: Grant Manager / Administrator | C2: 1 | D2: Full-Time | E2: Yr 1 | F2: 90000 | G2: 130000 | H2: =AVERAGE(F2,G2) -> 110000 | I2: 0.25 | J2: =H2*I2 -> 27500 | K2: =H2+J2 -> 137500
A3: 2 | B3: Nonprofit Bookkeeper / Payroll | C3: 1 | D3: Part-Time | E3: Yr 1 | F3: 45000 | G3: 65000 | H3: =AVERAGE(F3,G3) -> 55000 | I3: 0.25 | J3: =H3*I3 -> 13750 | K3: =H3+J3 -> 68750
A4: 3 | B4: Association Director | C4: 1 | D4: Full-Time | E4: Yr 2 | F4: 110000 | G4: 150000 | H4: =AVERAGE(F4,G4) -> 130000 | I4: 0.25 | J4: =H4*I4 -> 32500 | K4: =H4+J4 -> 162500
B5: TOTAL NONPROFIT PERSONNEL | K5: =SUM(K2:K4) -> 368750

Sheet Nonprofit Revenue
A1: # | B1: Revenue Stream | C1: Frequency | D1: Type | E1: Year 1 Low | F1: Year 1 High | G1: Year 1 Mid | H1: Year 3 Target | I1: Notes
A2: 1 | B2: Foundation Grants (501c3 required) | C2: Per cycle | D2: Grants | E2: 500000 | F2: 2000000 | G2: =AVERAGE(E2,F2) -> 1250000 | H2: 0 | I2: Open Phil, SFF, Sloan, Hewlett
A3: 2 | B3: Federal Grants (nonprofit required) | C3: Per cycle | D3: Grants | E3: 250000 | F3: 1000000 | G3: =AVERAGE(E3,F3) -> 625000 | H3: 0 | I3: Select federal programs
A4: 3 | B4: Individual Donations | C4: Ongoing | D4: Donations | E4: 50000 | F4: 200000 | G4: =AVERAGE(E4,F4) -> 125000 | H4: 0 | I4: Donate page, campaigns
A5: 4 | B5: Association Dues (Year 2+) | C5: Annual | D5: Dues | E5: 0 | F5: 0 | G5: =AVERAGE(E5,F5) -> 0 | H5: 0 | I5: Launches Year 2
B6: TOTAL NONPROFIT REVENUE | E6: =SUM(E2:E5) -> 800000 | F6: =SUM(F2:F5) -> 3200000 | G6: =SUM(G2:G5) -> 2000000

Sheet Nonprofit Summary
A1: PRISM RESEARCH INSTITUTE 501(c)(3)
A2: Financial Summary
B4: Low | C4: High | D4: Mid
A5: EXPENSES
A6: Personnel (3 roles, fully loaded at 25%) | B6: ='Nonprofit Personnel'!K5 -> 368750 | C6: ='Nonprofit Personnel'!K5 -> 368750 | D6: ='Nonprofit Personnel'!K5 -> 368750
A7: Nonprofit Operations (admin, filing, insurance) | B7: 25000 | C7: 50000 | D7: =AVERAGE(B7,C7) -> 37500
A8: Contract Payments to PBC (grant-funded research) | B8: 0 | C8: 0 | D8: 0
A9: TOTAL NONPROFIT EXPENSES | B9: =B6+B7+B8 -> 393750 | C9: =C6+C7+C8 -> 418750 | D9: =D6+D7+D8 -> 406250
A11: REVENUE
A12: Foundation Grants (501c3 required) | B12: ='Nonprofit Revenue'!E2 -> 500000 | C12: ='Nonprofit Revenue'!F2 -> 2000000 | D12: ='Nonprofit Revenue'!G2 -> 1250000
A13: Federal Grants (nonprofit required) | B13: ='Nonprofit Revenue'!E3 -> 250000 | C13: ='Nonprofit Revenue'!F3 -> 1000000 | D13: ='Nonprofit Revenue'!G3 -> 625000
A14: Individual Donations | B14: ='Nonprofit Revenue'!E4 -> 50000 | C14: ='Nonprofit Revenue'!F4 -> 200000 | D14: ='Nonprofit Revenue'!G4 -> 125000
A15: Association Dues (Year 2+) | B15: ='Nonprofit Revenue'!E5 -> 0 | C15: ='Nonprofit Revenue'!F5 -> 0 | D15: ='Nonprofit Revenue'!G5 -> 0
A16: TOTAL NONPROFIT REVENUE | B16: =B12+B13+B14+B15 -> 800000 | C16: =C12+C13+C14+C15 -> 3200000 | D16: =D12+D13+D14+D15 -> 2000000
A18: NET (Revenue minus Expenses) | B18: =B16-B9 -> 406250 | C18: =C16-C9 -> 2781250 | D18: =D16-D9 -> 1593750
A20: NOTE: Net surplus funds research contracts to the PBC.
A21: The "Contract Payments to PBC" expense line = the PBC "Contract Revenue from Nonprofit" line.
A22: When you set one, update the other to match.
